OrbitPy/__init__.py
OrbitPy/orbit.py
OrbitPy-0.0.0.dist-info/LICENSE
OrbitPy-0.0.0.dist-info/METADATA
OrbitPy-0.0.0.dist-info/WHEEL
OrbitPy-0.0.0.dist-info/top_level.txt
OrbitPy-0.0.0.dist-info/RECORD
