Metadata-Version: 2.1
Name: OrbitPy
Version: 0.0.0
Summary: A Python library that deals with different fields of science.
Home-page: https://github.com/PyndyalaCoder/OrbitPy
Author: Siddhu Pendyala
Author-email: elcientifico.pendyala@gmail.com
License: MIT
Project-URL: Bug Tracker, https://github.com/PyndyalaCoder/OrbitPy/issues
License-File: LICENSE
Requires-Dist: requests
